Metadata-Version: 1.0
Name: swarm-war
Version: 1.0.0b1
Summary: A Facebook game engine written with Django.
Home-page: http://seanhayes.name/
Author: Seán Hayes
Author-email: sean@seanhayes.name
License: UNKNOWN
Download-URL: https://github.com/SeanHayes/swarm-war
Keywords: django facebook game engine
Platform: UNKNOWN
Classifier: Development Status :: 4 - Beta
Classifier: Framework :: Django
Classifier: Intended Audience :: Developers
Classifier: License :: OSI Approved :: GNU Affero General Public License v3
Classifier: Operating System :: OS Independent
Classifier: Programming Language :: Python
Classifier: Programming Language :: Python :: 2.6
Classifier: Topic :: Internet :: WWW/HTTP :: Dynamic Content
Classifier: Topic :: Software Development :: Libraries
Classifier: Topic :: Software Development :: Libraries :: Python Modules
